cso_ireland_data/__init__.py
cso_ireland_data/cso_ireland_data.py
cso_ireland_data-0.0.3.dist-info/METADATA
cso_ireland_data-0.0.3.dist-info/WHEEL
cso_ireland_data-0.0.3.dist-info/top_level.txt
cso_ireland_data-0.0.3.dist-info/RECORD
